{"name":"searching_by_ambiguious_keyword_should_display_the_disambiguation_page","testCaseName":"Lab5SerenityJUnit.features.search.SearchByKeywordStory","userStory":{"id":"Lab5SerenityJUnit.features.search.SearchByKeywordStory","storyName":"Search by keyword story","storyClassName":"Lab5SerenityJUnit.features.search.SearchByKeywordStory","path":"Lab5SerenityJUnit.features.search","type":"story"},"featureTag":{"name":"Search/Search by keyword story","type":"story"},"title":"Searching by ambiguious keyword should display the disambiguation page","tags":[{"name":"Search/Search by keyword story","type":"story"}],"startTime":1620588761983,"duration":3,"annotatedResult":"PENDING","manual":false,"testSource":"JUnit","result":"PENDING"}